[
  {
    "lat": 35.546002,
    "lng": 139.56082497,
    "filename": "photo001.jpg"
  },
  {
    "lat": 35.546002,
    "lng": 139.56082497,
    "filename": "photo002.jpg"
  },
  {
    "lat": 35.546002,
    "lng": 139.56082497,
    "filename": "photo003.jpg"
  },
  {
    "lat": 35.546002,
    "lng": 139.56082497,
    "filename": "photo004.jpg"
  },
  {
    "lat": 35.546201,
    "lng": 139.561438,
    "filename": "photo005.jpg"
  },
  {
    "lat": 35.546201,
    "lng": 139.561438,
    "filename": "photo006.jpg"
  },
  {
    "lat": 35.546201,
    "lng": 139.561438,
    "filename": "photo007.jpg"
  },
  {
    "lat": 35.546201,
    "lng": 139.561438,
    "filename": "photo008.jpg"
  },
  {
    "lat": 35.546201,
    "lng": 139.561438,
    "filename": "photo009.jpg"
  },
  {
    "lat": 35.546201,
    "lng": 139.561438,
    "filename": "photo010.jpg"
  },
  {
    "lat": 35.546201,
    "lng": 139.561438,
    "filename": "photo011.jpg"
  },
  {
    "lat": 35.546201,
    "lng": 139.561438,
    "filename": "photo012.jpg"
  },
  {
    "lat": 35.546201,
    "lng": 139.561438,
    "filename": "photo013.jpg"
  },
  {
    "lat": 35.546201,
    "lng": 139.561438,
    "filename": "photo014.jpg"
  },
  {
    "lat": 35.546201,
    "lng": 139.561438,
    "filename": "photo015.jpg"
  },
  {
    "lat": 35.546201,
    "lng": 139.561438,
    "filename": "photo016.jpg"
  },
  {
    "lat": 35.546201,
    "lng": 139.561438,
    "filename": "photo017.jpg"
  },
  {
    "lat": 35.546737,
    "lng": 139.56168297,
    "filename": "photo018.jpg"
  },
  {
    "lat": 35.546737,
    "lng": 139.56168297,
    "filename": "photo019.jpg"
  },
  {
    "lat": 35.546737,
    "lng": 139.56168297,
    "filename": "photo020.jpg"
  },
  {
    "lat": 35.546737,
    "lng": 139.56168297,
    "filename": "photo021.jpg"
  },
  {
    "lat": 35.546737,
    "lng": 139.56168297,
    "filename": "photo022.jpg"
  },
  {
    "lat": 35.546737,
    "lng": 139.56168297,
    "filename": "photo023.jpg"
  },
  {
    "lat": 35.546737,
    "lng": 139.56168297,
    "filename": "photo024.jpg"
  },
  {
    "lat": 35.546737,
    "lng": 139.56168297,
    "filename": "photo025.jpg"
  },
  {
    "lat": 35.546737,
    "lng": 139.56168297,
    "filename": "photo026.jpg"
  },
  {
    "lat": 35.546238,
    "lng": 139.561684,
    "filename": "photo027.jpg"
  },
  {
    "lat": 35.546238,
    "lng": 139.561684,
    "filename": "photo028.jpg"
  },
  {
    "lat": 35.546238,
    "lng": 139.561684,
    "filename": "photo029.jpg"
  },
  {
    "lat": 35.546238,
    "lng": 139.561684,
    "filename": "photo030.jpg"
  },
  {
    "lat": 35.546238,
    "lng": 139.561684,
    "filename": "photo031.jpg"
  },
  {
    "lat": 35.546238,
    "lng": 139.561684,
    "filename": "photo032.jpg"
  },
  {
    "lat": 35.54665297,
    "lng": 139.56155797,
    "filename": "photo033.jpg"
  },
  {
    "lat": 35.54665297,
    "lng": 139.56155797,
    "filename": "photo034.jpg"
  },
  {
    "lat": 35.54665297,
    "lng": 139.56155797,
    "filename": "photo035.jpg"
  },
  {
    "lat": 35.546582,
    "lng": 139.56166997,
    "filename": "photo036.jpg"
  },
  {
    "lat": 35.54583997,
    "lng": 139.56116,
    "filename": "photo037.jpg"
  },
  {
    "lat": 35.54583997,
    "lng": 139.56116,
    "filename": "photo038.jpg"
  },
  {
    "lat": 35.54583997,
    "lng": 139.56116,
    "filename": "photo039.jpg"
  },
  {
    "lat": 35.54583997,
    "lng": 139.56116,
    "filename": "photo040.jpg"
  },
  {
    "lat": 35.54554,
    "lng": 139.560675,
    "filename": "photo041.jpg"
  },
  {
    "lat": 35.54554,
    "lng": 139.560675,
    "filename": "photo042.jpg"
  },
  {
    "lat": 35.54554,
    "lng": 139.560675,
    "filename": "photo043.jpg"
  },
  {
    "lat": 35.54464897,
    "lng": 139.560111,
    "filename": "photo044.jpg"
  },
  {
    "lat": 35.54464897,
    "lng": 139.560111,
    "filename": "photo045.jpg"
  },
  {
    "lat": 35.54464897,
    "lng": 139.560111,
    "filename": "photo046.jpg"
  },
  {
    "lat": 35.54464897,
    "lng": 139.560111,
    "filename": "photo047.jpg"
  },
  {
    "lat": 35.54464897,
    "lng": 139.560111,
    "filename": "photo048.jpg"
  },
  {
    "lat": 35.54464897,
    "lng": 139.560111,
    "filename": "photo049.jpg"
  },
  {
    "lat": 35.54464897,
    "lng": 139.560111,
    "filename": "photo050.jpg"
  },
  {
    "lat": 35.54464897,
    "lng": 139.560111,
    "filename": "photo051.jpg"
  },
  {
    "lat": 35.54464897,
    "lng": 139.560111,
    "filename": "photo052.jpg"
  },
  {
    "lat": 35.54464897,
    "lng": 139.560111,
    "filename": "photo053.jpg"
  },
  {
    "lat": 35.54464897,
    "lng": 139.560111,
    "filename": "photo054.jpg"
  },
  {
    "lat": 35.54464897,
    "lng": 139.560111,
    "filename": "photo055.jpg"
  },
  {
    "lat": 35.54464897,
    "lng": 139.560111,
    "filename": "photo056.jpg"
  },
  {
    "lat": 35.54464897,
    "lng": 139.560111,
    "filename": "photo057.jpg"
  },
  {
    "lat": 35.54464897,
    "lng": 139.560111,
    "filename": "photo058.jpg"
  },
  {
    "lat": 35.54464897,
    "lng": 139.560111,
    "filename": "photo059.jpg"
  },
  {
    "lat": 35.54464897,
    "lng": 139.560111,
    "filename": "photo060.jpg"
  },
  {
    "lat": 35.54464897,
    "lng": 139.560111,
    "filename": "photo061.jpg"
  },
  {
    "lat": 35.54464897,
    "lng": 139.560111,
    "filename": "photo062.jpg"
  },
  {
    "lat": 35.54464897,
    "lng": 139.560111,
    "filename": "photo063.jpg"
  },
  {
    "lat": 35.54464897,
    "lng": 139.560111,
    "filename": "photo064.jpg"
  },
  {
    "lat": 35.54464897,
    "lng": 139.560111,
    "filename": "photo065.jpg"
  },
  {
    "lat": 35.54464897,
    "lng": 139.560111,
    "filename": "photo066.jpg"
  },
  {
    "lat": 35.54464897,
    "lng": 139.560111,
    "filename": "photo067.jpg"
  },
  {
    "lat": 35.54464897,
    "lng": 139.560111,
    "filename": "photo068.jpg"
  },
  {
    "lat": 35.54464897,
    "lng": 139.560111,
    "filename": "photo069.jpg"
  },
  {
    "lat": 35.54464897,
    "lng": 139.560111,
    "filename": "photo070.jpg"
  },
  {
    "lat": 35.54464897,
    "lng": 139.560111,
    "filename": "photo071.jpg"
  },
  {
    "lat": 35.54464897,
    "lng": 139.560111,
    "filename": "photo072.jpg"
  },
  {
    "lat": 35.54582297,
    "lng": 139.56188,
    "filename": "photo073.jpg"
  },
  {
    "lat": 35.54582297,
    "lng": 139.56188,
    "filename": "photo074.jpg"
  },
  {
    "lat": 35.54582297,
    "lng": 139.56188,
    "filename": "photo075.jpg"
  },
  {
    "lat": 35.54582297,
    "lng": 139.56188,
    "filename": "photo076.jpg"
  },
  {
    "lat": 35.54582297,
    "lng": 139.56188,
    "filename": "photo077.jpg"
  },
  {
    "lat": 35.54582297,
    "lng": 139.56188,
    "filename": "photo078.jpg"
  },
  {
    "lat": 35.54596697,
    "lng": 139.56131097,
    "filename": "photo079.jpg"
  },
  {
    "lat": 35.54596697,
    "lng": 139.56131097,
    "filename": "photo080.jpg"
  },
  {
    "lat": 35.54596697,
    "lng": 139.56131097,
    "filename": "photo081.jpg"
  },
  {
    "lat": 35.54596697,
    "lng": 139.56131097,
    "filename": "photo082.jpg"
  },
  {
    "lat": 35.54596697,
    "lng": 139.56131097,
    "filename": "photo083.jpg"
  },
  {
    "lat": 35.545864,
    "lng": 139.56124297,
    "filename": "photo084.jpg"
  },
  {
    "lat": 35.546002,
    "lng": 139.560435,
    "filename": "photo085.jpg"
  },
  {
    "lat": 35.546002,
    "lng": 139.560435,
    "filename": "photo086.jpg"
  },
  {
    "lat": 35.546002,
    "lng": 139.560435,
    "filename": "photo087.jpg"
  },
  {
    "lat": 35.546002,
    "lng": 139.560435,
    "filename": "photo088.jpg"
  },
  {
    "lat": 35.546002,
    "lng": 139.560435,
    "filename": "photo089.jpg"
  }
]